wizad/.DS_Store
wizad/__init__.py
wizad/bivariate.py
wizad/univariate.py
wizad-0.1.0.dist-info/METADATA
wizad-0.1.0.dist-info/WHEEL
wizad-0.1.0.dist-info/licenses/LICENSE
wizad-0.1.0.dist-info/RECORD
