Metadata-Version: 2.1
Name: wizad
Version: 0.1.0
Summary: A simple visualization library for univariate and bivariate analysis
Project-URL: Homepage, https://github.com/bala-srm/eda
Project-URL: Bug Tracker, https://github.com/bala-srm/eda/issues
Author-email: Balaji Sundararaman <bala@python4u.in>
License-File: LICENSE
Classifier: License :: OSI Approved :: MIT License
Classifier: Operating System :: OS Independent
Classifier: Programming Language :: Python :: 3.7
Requires-Python: >=3.7
